pyconst/__init__.py
pyconst/const.py
pyconst/slug.py
pyconst-2.0.0.dist-info/LICENSE
pyconst-2.0.0.dist-info/METADATA
pyconst-2.0.0.dist-info/WHEEL
pyconst-2.0.0.dist-info/top_level.txt
pyconst-2.0.0.dist-info/RECORD
