Metadata-Version: 2.1
Name: pyconst
Version: 2.0.0
Summary: PyConst one simple way to organize the constants
Home-page: https://github.com/valdergallo/pyconst
Author: valdergallo
Author-email: valdergallo@gmail.com
License: GPL-3.0
Download-URL: https://github.com/valdergallo/pyconst/tarball/2.0.0/
Keywords: constants,django,data,control
Platform: any
Classifier: Framework :: Django
Classifier: Operating System :: OS Independent
Classifier: Topic :: Utilities
Classifier: Programming Language :: Python
Classifier: Programming Language :: Python :: 2.6
Classifier: Programming Language :: Python :: 2.7
Classifier: Programming Language :: Python :: 3.3
Classifier: Programming Language :: Python :: 3.4
Classifier: Programming Language :: Python :: 3.5
Classifier: Programming Language :: Python :: 3.6
